langchain_sequential_thinking_tool-0.1.1.dist-info/licenses/LICENSE
sequential_thinking_tool/__init__.py
sequential_thinking_tool/models.py
sequential_thinking_tool/tool.py
langchain_sequential_thinking_tool-0.1.1.dist-info/METADATA
langchain_sequential_thinking_tool-0.1.1.dist-info/WHEEL
langchain_sequential_thinking_tool-0.1.1.dist-info/top_level.txt
langchain_sequential_thinking_tool-0.1.1.dist-info/RECORD
