Metadata-Version: 2.4
Name: langchain-sequential-thinking-tool
Version: 0.1.1
Summary: A LangChain tool implementing sequential thinking logic for structured problem-solving with tools .
Author-email: cognitive-glitch <intuitionwith@gmail.com>
Project-URL: Homepage, https://github.com/cognitive-glitch/langchain-sequential-thinking-tool
Project-URL: Bug Tracker, https://github.com/cognitive-glitch/langchain-sequential-thinking-tool/issues
Classifier: Programming Language :: Python :: 3
Classifier: License :: OSI Approved :: MIT License
Classifier: Operating System :: OS Independent
Classifier: Intended Audience :: Developers
Classifier: Topic :: Scientific/Engineering :: Artificial Intelligence
Classifier: Topic :: Software Development :: Libraries :: Python Modules
Requires-Python: >=3.8
License-File: LICENSE
Requires-Dist: langchain-core>=0.1
Requires-Dist: pydantic>=2.0
Requires-Dist: rich
Provides-Extra: dev
Requires-Dist: pytest>=8.3.5; extra == "dev"
Requires-Dist: build>=1.2.2; extra == "dev"
Requires-Dist: twine>=6.1.0; extra == "dev"
Dynamic: license-file
